rtspscan/__init__.py
rtspscan/rtspscan.py
rtspscan-1.0.2.dist-info/METADATA
rtspscan-1.0.2.dist-info/WHEEL
rtspscan-1.0.2.dist-info/entry_points.txt
rtspscan-1.0.2.dist-info/top_level.txt
rtspscan-1.0.2.dist-info/RECORD
