Metadata-Version: 2.4
Name: rtspscan
Version: 1.0.2
Summary: RtspScan is a Port Scanner and Streamer used to scan and open any camera connected to the internet.
Home-page: https://github.com/babaralijamali/RtspScan
Author: Babar Ali Jamali
Author-email: babar995@gmail.com
Classifier: Programming Language :: Python :: 3
Classifier: License :: OSI Approved :: MIT License
Classifier: Operating System :: OS Independent
Requires-Python: >=3.6
Requires-Dist: opencv-python
Dynamic: author
Dynamic: author-email
Dynamic: classifier
Dynamic: home-page
Dynamic: requires-dist
Dynamic: requires-python
Dynamic: summary
